privacy/qa/win/__init__.py
privacy.qa.win-0.0.1.dist-info/METADATA
privacy.qa.win-0.0.1.dist-info/WHEEL
privacy.qa.win-0.0.1.dist-info/top_level.txt
privacy.qa.win-0.0.1.dist-info/RECORD
